LICENSE
MANIFEST.in
README.rst
setup.cfg
setup.py
specio/__init__.py
specio/_version.py
specio/cli.py
specio.egg-info/PKG-INFO
specio.egg-info/SOURCES.txt
specio.egg-info/dependency_links.txt
specio.egg-info/entry_points.txt
specio.egg-info/requires.txt
specio.egg-info/top_level.txt
specio/core/__init__.py
specio/core/exceptions.py
specio/core/format.py
specio/core/functions.py
specio/core/request.py
specio/core/util.py
specio/core/tests/__init__.py
specio/core/tests/test_format.py
specio/core/tests/test_functions.py
specio/core/tests/test_request.py
specio/core/tests/test_util.py
specio/core/tests/data/20170410EDL_L01_cell01_c1.spc
specio/core/tests/data/20170410EDL_L01_cell01_c2.spc
specio/core/tests/data/20170410EDL_L01_cell01_c3.spc
specio/core/tests/data/__init__.py
specio/core/tests/data/__init__.pyc
specio/core/tests/data/spectra.foobar
specio/core/tests/data/spectra.notavalidext
specio/core/tests/data/__pycache__/__init__.cpython-36.pyc
specio/datasets/__init__.py
specio/datasets/path.py
specio/datasets/data/__init__.py
specio/datasets/data/__init__.pyc
specio/datasets/data/spectra.csv
specio/datasets/data/spectra.fsm
specio/datasets/data/spectra.mzml
specio/datasets/data/spectra.sp
specio/datasets/data/spectra.spc
specio/datasets/data/__pycache__/__init__.cpython-36.pyc
specio/plugins/__init__.py
specio/plugins/csv.py
specio/plugins/example.py
specio/plugins/fsm.py
specio/plugins/mzml.py
specio/plugins/mzxml.py
specio/plugins/sp.py
specio/plugins/spc.py
specio/plugins/tests/__init__.py
specio/plugins/tests/test_common.py
specio/plugins/tests/test_example.py
specio/plugins/tests/test_mzml.py
specio/plugins/tests/test_spc.py
specio/plugins/tests/data/__init__.py
specio/plugins/tests/data/__init__.pyc
specio/plugins/tests/data/spectra.foobar
specio/plugins/tests/data/spectra.notavalidext
specio/plugins/tests/data/__pycache__/__init__.cpython-36.pyc
specio/plugins/tests/data/spc/__init__.py
specio/plugins/tests/data/spc/__init__.pyc
specio/plugins/tests/data/spc/__pycache__/__init__.cpython-36.pyc
specio/plugins/tests/data/spc/single_file/-xy.spc
specio/plugins/tests/data/spc/single_file/__init__.py
