Metadata-Version: 1.1
Name: specio
Version: 0.1.0
Summary: specio: Python input/output for spectroscopic files.
Home-page: https://github.com/paris-saclay-cds/specio
Author: Guillaume Lemaitre
Author-email: glemaitre58@gmail.com
License: BSD3
Platform: OS Independent
Classifier: Environment :: Console
Classifier: Intended Audience :: Science/Research
Classifier: License :: OSI Approved
Classifier: Operating System :: OS Independent
Classifier: Programming Language :: Python :: 2.7
Classifier: Programming Language :: Python :: 3.5
Classifier: Programming Language :: Python :: 3.6
Classifier: Topic :: Scientific/Engineering
